GTInformation/__init__.py
Growtopia_Info-2.1.5.dist-info/LICENSE.txt
Growtopia_Info-2.1.5.dist-info/METADATA
Growtopia_Info-2.1.5.dist-info/WHEEL
Growtopia_Info-2.1.5.dist-info/top_level.txt
Growtopia_Info-2.1.5.dist-info/RECORD
