Metadata-Version: 2.1
Name: Growtopia-Info
Version: 2.1.5
Summary: This code can search any information in Growtopia, including Sprite, Description, Player Online, and more!
Home-page: https://github.com/Gabrielbjb/growtopia-info
Author: Gabrielbjb
Author-email: gabrielbjb@protonmail.com
License: MIT
Keywords: Growtopia,Growtopia Wiki,Growtopia Fandom
Classifier: Development Status :: 5 - Production/Stable
Classifier: Intended Audience :: Education
Classifier: Operating System :: OS Independent
Classifier: License :: OSI Approved :: MIT License
Classifier: Programming Language :: Python :: 3
License-File: LICENSE.txt
